CHANGELOG.rst
MANIFEST.in
README.rst
catasto.qml
requirements-dev.txt
requirements.txt
setup.cfg
setup.py
bgeo/__init__.py
bgeo.catasto.egg-info/PKG-INFO
bgeo.catasto.egg-info/SOURCES.txt
bgeo.catasto.egg-info/dependency_links.txt
bgeo.catasto.egg-info/entry_points.txt
bgeo.catasto.egg-info/namespace_packages.txt
bgeo.catasto.egg-info/not-zip-safe
bgeo.catasto.egg-info/requires.txt
bgeo.catasto.egg-info/top_level.txt
bgeo/catasto/__init__.py
bgeo/catasto/apps.py
bgeo/catasto/cxf.py
bgeo/catasto/ogr.py
bgeo/catasto/test_10_cxf.txt
docs/GPLv3.txt
docs/HISTORY.txt