Metadata-Version: 1.1
Name: bgeo.catasto
Version: 0.3.1
Summary: Italian land registry utilities
Home-page: http://github.com/bopen/bgeo.catasto
Author: Alessandro Amici
Author-email: a.amici@bopen.eu
License: GPL
Platform: UNKNOWN
Classifier: Programming Language :: Python
Classifier: Development Status :: 3 - Alpha
Classifier: Environment :: Console
Classifier: License :: OSI Approved :: GNU General Public License (GPL)
Classifier: Programming Language :: Python
Classifier: Programming Language :: Python :: 2
Classifier: Programming Language :: Python :: 2.7
Classifier: Programming Language :: Python :: 3
Classifier: Programming Language :: Python :: 3.5
Classifier: Topic :: Scientific/Engineering :: GIS
